{
  "time_range": {
    "start": "2025-07-10T07:06:00",
    "end": "2025-07-10T07:08:00"
  },
  "group_id": "cc8f1d29-7a49-4975-95dc-7ac94aefc04b",
  "users": [
    {
      "user_id": "VaTnrRc18Facn5GYEcDyYNPyY7p2",
      "name": "juno",
      "speech_count": 4,
      "speech_duration": 57.62
    },
    {
      "user_id": "MehACGvYsfVaGnq5utXQupmAIji2",
      "name": "Tark",
      "speech_count": 5,
      "speech_duration": 40.74
    },
    {
      "user_id": "50SHBajxtge2rmatUM7OU7MPeu32",
      "name": "Meteora",
      "speech_count": 2,
      "speech_duration": 13.94
    }
  ],
  "raw_tables": {
    "speech_transcripts": [
      {
        "text": "呃，不是那种就是有什么利益关系啊，或者说在有一些社交的压迫下的一种一种情感，就是可以完全凭借着自己的兴趣跟爱好去找到一些志同道合的人。",
        "session_id": "9c2f05d3-19d1-4cf6-b5a4-124ec6fba4a3",
        "duration": 14.76,
        "start": "2025-07-10T07:06:11.739090",
        "group_id": "cc8f1d29-7a49-4975-95dc-7ac94aefc04b",
        "speaker": "Tark",
        "end": "2025-07-10T07:06:26.499090",
        "transcript_id": "ca11565a-ec1b-420c-bab2-ae13428a21ea",
        "user_id": "MehACGvYsfVaGnq5utXQupmAIji2",
        "group_key": "groupD"
      },
      {
        "text": "是我分析的两个原因。",
        "session_id": "9c2f05d3-19d1-4cf6-b5a4-124ec6fba4a3",
        "duration": 2.98,
        "start": "2025-07-10T07:06:26.519090",
        "group_id": "cc8f1d29-7a49-4975-95dc-7ac94aefc04b",
        "speaker": "Tark",
        "end": "2025-07-10T07:06:29.499090",
        "transcript_id": "691c3149-b8ce-4026-9246-4768c630f7b4",
        "user_id": "MehACGvYsfVaGnq5utXQupmAIji2",
        "group_key": "groupD"
      },
      {
        "text": "我觉得这样子的话，就是现在社会来说，就更准确更高效的一个交朋友的方法。你有兴趣，那我们在这个世界上可以一起玩，就成本也会降低，就会像以前一样，你交一个朋友需要很久才能深入去。",
        "session_id": "9c2f05d3-19d1-4cf6-b5a4-124ec6fba4a3",
        "duration": 18.28,
        "start": "2025-07-10T07:06:30.459090",
        "group_id": "cc8f1d29-7a49-4975-95dc-7ac94aefc04b",
        "speaker": "juno",
        "end": "2025-07-10T07:06:48.739090",
        "transcript_id": "d4e05f80-0551-4a22-a856-ddef37664d7e",
        "user_id": "VaTnrRc18Facn5GYEcDyYNPyY7p2",
        "group_key": "groupD"
      },
      {
        "text": "走路对方的心。这种。",
        "session_id": "9c2f05d3-19d1-4cf6-b5a4-124ec6fba4a3",
        "duration": 2.88,
        "start": "2025-07-10T07:06:48.739090",
        "group_id": "cc8f1d29-7a49-4975-95dc-7ac94aefc04b",
        "speaker": "unknown",
        "end": "2025-07-10T07:06:51.619090",
        "transcript_id": "4dcdbb12-c33b-4df4-994c-723f964113b8",
        "user_id": "unknown",
        "group_key": "groupD"
      },
      {
        "text": "而且，他也不是身边的人，你可以在网上找，所以就是空间上，你就没有那么大的限制。",
        "session_id": "9c2f05d3-19d1-4cf6-b5a4-124ec6fba4a3",
        "duration": 9.64,
        "start": "2025-07-10T07:06:52.139090",
        "group_id": "cc8f1d29-7a49-4975-95dc-7ac94aefc04b",
        "speaker": "juno",
        "end": "2025-07-10T07:07:01.779090",
        "transcript_id": "4694e691-6a23-4da8-86ef-a22853f33f26",
        "user_id": "VaTnrRc18Facn5GYEcDyYNPyY7p2",
        "group_key": "groupD"
      },
      {
        "text": "你有的时候，你约一个单子，可能嗯一起出去旅游什么的你从这里去，从那那边一起去都可以。就不是你的同学，不是你同事，这种在身边的朋友。",
        "session_id": "9c2f05d3-19d1-4cf6-b5a4-124ec6fba4a3",
        "duration": 12.84,
        "start": "2025-07-10T07:07:03.139090",
        "group_id": "cc8f1d29-7a49-4975-95dc-7ac94aefc04b",
        "speaker": "juno",
        "end": "2025-07-10T07:07:15.979090",
        "transcript_id": "6aa26ed6-6f8b-480e-8c82-e9d721dfa0e3",
        "user_id": "VaTnrRc18Facn5GYEcDyYNPyY7p2",
        "group_key": "groupD"
      },
      {
        "text": "然后。",
        "session_id": "9c2f05d3-19d1-4cf6-b5a4-124ec6fba4a3",
        "duration": 1.26,
        "start": "2025-07-10T07:07:16.539090",
        "group_id": "cc8f1d29-7a49-4975-95dc-7ac94aefc04b",
        "speaker": "unknown",
        "end": "2025-07-10T07:07:17.799090",
        "transcript_id": "e14b3b0e-5e9d-4777-9a09-aef4f169f5a6",
        "user_id": "unknown",
        "group_key": "groupD"
      },
      {
        "text": "也是现在大家对自己的自我认同感更高，所以对自己兴趣更关注。所以他就是能了解到这些呃，有相同共同兴趣爱好的人，就是更细化去分那些爱好吧。",
        "session_id": "9c2f05d3-19d1-4cf6-b5a4-124ec6fba4a3",
        "duration": 16.86,
        "start": "2025-07-10T07:07:19.099090",
        "group_id": "cc8f1d29-7a49-4975-95dc-7ac94aefc04b",
        "speaker": "juno",
        "end": "2025-07-10T07:07:35.959090",
        "transcript_id": "0654063d-02fc-4882-8cc5-842a68a76166",
        "user_id": "VaTnrRc18Facn5GYEcDyYNPyY7p2",
        "group_key": "groupD"
      },
      {
        "text": "我们是不是现在要把这个任务的总结，就是做成这个笔记形式？",
        "session_id": "9c2f05d3-19d1-4cf6-b5a4-124ec6fba4a3",
        "duration": 6.84,
        "start": "2025-07-10T07:07:39.939090",
        "group_id": "cc8f1d29-7a49-4975-95dc-7ac94aefc04b",
        "speaker": "Meteora-1",
        "end": "2025-07-10T07:07:46.779090",
        "transcript_id": "83dcca95-48bb-4efa-a1dd-1059c3fa1a5e",
        "user_id": "50SHBajxtge2rmatUM7OU7MPeu32",
        "group_key": "groupD"
      },
      {
        "text": "这块就是分点的去网页，那可能我们要总结一下这个刚才大家的这个。",
        "session_id": "9c2f05d3-19d1-4cf6-b5a4-124ec6fba4a3",
        "duration": 7.1,
        "start": "2025-07-10T07:07:46.879090",
        "group_id": "cc8f1d29-7a49-4975-95dc-7ac94aefc04b",
        "speaker": "Meteora-1",
        "end": "2025-07-10T07:07:53.979090",
        "transcript_id": "3cce5839-8e03-41a2-9ac9-cd34c67ec38e",
        "user_id": "50SHBajxtge2rmatUM7OU7MPeu32",
        "group_key": "groupD"
      },
      {
        "text": "这个发现。",
        "session_id": "9c2f05d3-19d1-4cf6-b5a4-124ec6fba4a3",
        "duration": 1.52,
        "start": "2025-07-10T07:07:53.979090",
        "group_id": "cc8f1d29-7a49-4975-95dc-7ac94aefc04b",
        "speaker": "unknown",
        "end": "2025-07-10T07:07:55.499090",
        "transcript_id": "8676add3-b234-4207-b03e-b957253cae48",
        "user_id": "unknown",
        "group_key": "groupD"
      },
      {
        "text": "是，作为警长要总结发言。",
        "session_id": "9c2f05d3-19d1-4cf6-b5a4-124ec6fba4a3",
        "duration": 3.82,
        "start": "2025-07-10T07:07:55.779090",
        "group_id": "cc8f1d29-7a49-4975-95dc-7ac94aefc04b",
        "speaker": "Tark",
        "end": "2025-07-10T07:07:59.599090",
        "transcript_id": "93e1556c-d9ef-4ddc-aa63-26864e0a3a42",
        "user_id": "MehACGvYsfVaGnq5utXQupmAIji2",
        "group_key": "groupD"
      },
      {
        "text": "呃。",
        "session_id": "9c2f05d3-19d1-4cf6-b5a4-124ec6fba4a3",
        "duration": 1.68,
        "start": "2025-07-10T07:07:59.599090",
        "group_id": "cc8f1d29-7a49-4975-95dc-7ac94aefc04b",
        "speaker": "Tark-1",
        "end": "2025-07-10T07:08:01.279090",
        "transcript_id": "c9c9393d-7d75-403d-938e-b8a369efe5c5",
        "user_id": "MehACGvYsfVaGnq5utXQupmAIji2",
        "group_key": "groupD"
      },
      {
        "text": "年轻人之间，他的那个呃，通过找搭子的这样一个途径吧，可以去呃构建就是只只关注我们的共同兴趣目标，找到这项的伙伙，这个同学或者伙伴而。",
        "session_id": "9c2f05d3-19d1-4cf6-b5a4-124ec6fba4a3",
        "duration": 17.5,
        "start": "2025-07-10T07:05:54.239090",
        "group_id": "cc8f1d29-7a49-4975-95dc-7ac94aefc04b",
        "speaker": "Tark",
        "end": "2025-07-10T07:06:11.739090",
        "transcript_id": "742003be-c532-46ae-92b5-c4bfc3e661b2",
        "user_id": "MehACGvYsfVaGnq5utXQupmAIji2",
        "group_key": "groupD"
      }
    ],
    "note_edit_history": [
      {
        "affectedText": "将个人的需求和爱好分类，结交不同的朋友，以达到更准确、更高效，在数量和形式上更加自由。数字化孤独-主动适应社会变化的选择；亲密关系的降级-浅社交关系，维系成本变低\n\n在“搭子”社交中，社交的“越界”行为和侵犯隐私的行为被有效控制，双方在相互理解和尊重的基 础上，心照不宣地建立起了明确的社交边界。\n\n尽管现代社会的人们在物理上更加接近，社交网络也更为广泛，但真正的社区感和归属感正在逐渐消失。这一点在青年人的“找搭子”行为中得到了体现，表面上的社交网络扩大了，实际上的人际深度却在缩小。\n\n趣缘关系体现了个体自由选择和参与的社交模式，与马克 思关于人的社会性理念相呼应。它基于兴趣爱好构建了一个自由平等的社会联系网络，不同于传统关系， 更强调个体在社交中的自主性和独立性。“搭子”社交作为一种新兴形式，正是基于这种趣缘关系满足 了青年的社交需求，在促进个体在平等和自由的环境中探索个人兴趣，推动了社交形式的创新和发展。\n\n人类有一个基本的需要，那就是与他人建立持久且有意义的关系。当这种需要得不到满足时，个体可能会经历心理疼痛，包括孤独感和不幸福感。热衷于寻找“搭子”的行为，尽管在表面上看似增加了社交机会，但由于这些关系缺乏深度和持久性，难以满足归属需要，从而可能导致个体感到更加孤独和不满足\n\n年轻人通过找“搭子”这一途径，构筑起基于共同目标抑或兴趣的伙伴关系，克服原子化 状态。",
        "hasList": false,
        "userId": "VaTnrRc18Facn5GYEcDyYNPyY7p2",
        "charCount": 592,
        "delta": [
          {
            "delete": 592
          }
        ],
        "summary": "删除文字",
        "hasHeader": false,
        "updatedAt": "2025-07-10T07:06:37.349Z",
        "isDelete": true
      },
      {
        "affectedText": "将个人的需求和爱好分类，结交不同的朋友，以达到更准确、更高效，在数量和形式上更加自由。数字化孤独-主动适应社会变化的选择；亲密关系的降级-浅社交关系，维系成本变低\n\n在“搭子”社交中，社交的“越界”行为和侵犯隐私的行为被有效控制，双方在相互理解和尊重的基 础上，心照不宣地建立起了明确的社交边界。\n\n尽管现代社会的人们在物理上更加接近，社交网络也更为广泛，但真正的社区感和归属感正在逐渐消失。这一点在青年人的“找搭子”行为中得到了体现，表面上的社交网络扩大了，实际上的人际深度却在缩小。\n\n趣缘关系体现了个体自由选择和参与的社交模式，与马克 思关于人的社会性理念相呼应。它基于兴趣爱好构建了一个自由平等的社会联系网络，不同于传统关系， 更强调个体在社交中的自主性和独立性。“搭子”社交作为一种新兴形式，正是基于这种趣缘关系满足 了青年的社交需求，在促进个体在平等和自由的环境中探索个人兴趣，推动了社交形式的创新和发展。\n\n人类有一个基本的需要，那就是与他人建立持久且有意义的关系。当这种需要得不到满足时，个体可能会经历心理疼痛，包括孤独感和不幸福感。热衷于寻找“搭子”的行为，尽管在表面上看似增加了社交机会，但由于这些关系缺乏深度和持久性，难以满足归属需要，从而可能导致个体感到更加孤独和不满足\n\n年轻人通过找“搭子”这一途径，构筑起基于共同目标抑或兴趣的伙伴关系，克服原子化 状态。",
        "hasList": false,
        "userId": "MehACGvYsfVaGnq5utXQupmAIji2",
        "charCount": 592,
        "delta": [
          {
            "delete": 592
          }
        ],
        "summary": "删除文字",
        "hasHeader": false,
        "updatedAt": "2025-07-10T07:06:04.100Z",
        "isDelete": true
      }
    ],
    "pageBehaviorLogs": {
      "Tark": {
        "user": {
          "session_id": "9c2f05d3-19d1-4cf6-b5a4-124ec6fba4a3",
          "user_id": "MehACGvYsfVaGnq5utXQupmAIji2",
          "group_id": "cc8f1d29-7a49-4975-95dc-7ac94aefc04b",
          "userName": "Tark"
        },
        "windowRanges": {
          "windowStart": "2025-07-10T07:05:50.000Z",
          "windowEnd": "2025-07-10T07:08:00.000Z"
        },
        "tabHistory": [
          {
            "title": "Collaborative Platform",
            "timestamp": "2025-07-10T07:05:50.158Z",
            "tabId": 1958191049,
            "url": "https://collaborative-ai-chatbot.web.app/#/personal-dashboard/Tark",
            "tabBehaviorLogs": [
              {
                "type": "mousemove",
                "startTime": "2025-07-10T07:05:54.396Z",
                "endTime": "2025-07-10T07:05:54.896Z",
                "action_count": 2,
                "startPosition": {
                  "y": 3,
                  "x": 626
                },
                "endPosition": {
                  "y": 201,
                  "x": 645
                }
              },
              {
                "type": "scroll",
                "startTime": "2025-07-10T07:05:55.019Z",
                "endTime": "2025-07-10T07:06:06.344Z",
                "action_count": 2,
                "minDepth": 1.0353909716194059,
                "maxDepth": 1.0353909716194059
              },
              {
                "type": "mousemove",
                "startTime": "2025-07-10T07:06:07.762Z",
                "endTime": "2025-07-10T07:06:24.658Z",
                "action_count": 6,
                "startPosition": {
                  "y": 213,
                  "x": 649
                },
                "endPosition": {
                  "y": 489,
                  "x": 864
                }
              }
            ]
          }
        ]
      },
      "juno": {
        "user": {
          "session_id": "9c2f05d3-19d1-4cf6-b5a4-124ec6fba4a3",
          "user_id": "VaTnrRc18Facn5GYEcDyYNPyY7p2",
          "group_id": "cc8f1d29-7a49-4975-95dc-7ac94aefc04b",
          "userName": "juno"
        },
        "windowRanges": {
          "windowStart": "2025-07-10T07:05:50.000Z",
          "windowEnd": "2025-07-10T07:08:00.000Z"
        },
        "tabHistory": [
          {
            "title": "Collaborative Platform",
            "timestamp": "2025-07-10T07:05:52.248Z",
            "tabId": 1924860374,
            "url": "https://collaborative-ai-chatbot.web.app/#/personal-dashboard/juno",
            "tabBehaviorLogs": [
              {
                "type": "scroll",
                "startTime": "2025-07-10T07:06:27.375Z",
                "endTime": "2025-07-10T07:06:27.375Z",
                "action_count": 1,
                "minDepth": 1.0165820436429251,
                "maxDepth": 1.0165820436429251
              },
              {
                "type": "mousemove",
                "startTime": "2025-07-10T07:06:28.113Z",
                "endTime": "2025-07-10T07:07:50.700Z",
                "action_count": 7,
                "startPosition": {
                  "y": 1,
                  "x": 342
                },
                "endPosition": {
                  "y": 372,
                  "x": 1069
                }
              },
              {
                "type": "scroll",
                "startTime": "2025-07-10T07:07:51.203Z",
                "endTime": "2025-07-10T07:07:51.203Z",
                "action_count": 1,
                "minDepth": 1.0165820436429251,
                "maxDepth": 1.0165820436429251
              },
              {
                "type": "mousemove",
                "startTime": "2025-07-10T07:07:51.485Z",
                "endTime": "2025-07-10T07:07:51.485Z",
                "action_count": 1,
                "startPosition": {
                  "y": 437,
                  "x": 458
                },
                "endPosition": {
                  "y": 437,
                  "x": 458
                }
              },
              {
                "type": "scroll",
                "startTime": "2025-07-10T07:07:51.935Z",
                "endTime": "2025-07-10T07:07:51.935Z",
                "action_count": 1,
                "minDepth": 1.0165820436429251,
                "maxDepth": 1.0165820436429251
              }
            ]
          },
          {
            "title": "搭子文化：年轻人的浅社交需求与社会变迁",
            "timestamp": "2025-07-10T07:05:52.248Z",
            "tabId": 1924860476,
            "url": "https://www.hbfs.edu.cn/gqt/84/3f/c4425a295999/page.psp",
            "tabBehaviorLogs": [
              {
                "type": "mousemove",
                "startTime": "2025-07-10T07:06:19.514Z",
                "endTime": "2025-07-10T07:06:26.493Z",
                "action_count": 3,
                "startPosition": {
                  "y": 15,
                  "x": 435
                },
                "endPosition": {
                  "y": 395,
                  "x": 851
                }
              }
            ]
          },
          {
            "title": "中国年轻人以“搭子文化”应对离婚养老 | 联合早报",
            "timestamp": "2025-07-10T07:05:52.248Z",
            "tabId": 1924860473,
            "url": "https://www.zaobao.com/news/china/story20240204-1466321",
            "tabBehaviorLogs": [
              {
                "type": "mousemove",
                "startTime": "2025-07-10T07:05:56.554Z",
                "endTime": "2025-07-10T07:05:56.554Z",
                "action_count": 1,
                "startPosition": {
                  "y": 7,
                  "x": 600
                },
                "endPosition": {
                  "y": 7,
                  "x": 600
                }
              },
              {
                "type": "scroll",
                "startTime": "2025-07-10T07:05:56.706Z",
                "endTime": "2025-07-10T07:05:56.706Z",
                "action_count": 1,
                "minDepth": 0.00025965595972766276,
                "maxDepth": 0.00025965595972766276
              },
              {
                "type": "mousemove",
                "startTime": "2025-07-10T07:05:57.732Z",
                "endTime": "2025-07-10T07:05:57.732Z",
                "action_count": 1,
                "startPosition": {
                  "y": 405,
                  "x": 844
                },
                "endPosition": {
                  "y": 405,
                  "x": 844
                }
              },
              {
                "type": "scroll",
                "startTime": "2025-07-10T07:05:57.804Z",
                "endTime": "2025-07-10T07:05:57.804Z",
                "action_count": 1,
                "minDepth": 0.09814994933349054,
                "maxDepth": 0.09814994933349054
              },
              {
                "type": "mousemove",
                "startTime": "2025-07-10T07:05:58.243Z",
                "endTime": "2025-07-10T07:05:58.243Z",
                "action_count": 1,
                "startPosition": {
                  "y": 400,
                  "x": 833
                },
                "endPosition": {
                  "y": 400,
                  "x": 833
                }
              },
              {
                "type": "scroll",
                "startTime": "2025-07-10T07:05:58.463Z",
                "endTime": "2025-07-10T07:05:58.463Z",
                "action_count": 1,
                "minDepth": 0.21123011612884413,
                "maxDepth": 0.21123011612884413
              },
              {
                "type": "mousemove",
                "startTime": "2025-07-10T07:05:58.839Z",
                "endTime": "2025-07-10T07:05:58.839Z",
                "action_count": 1,
                "startPosition": {
                  "y": 391,
                  "x": 813
                },
                "endPosition": {
                  "y": 391,
                  "x": 813
                }
              },
              {
                "type": "scroll",
                "startTime": "2025-07-10T07:05:59.687Z",
                "endTime": "2025-07-10T07:05:59.687Z",
                "action_count": 1,
                "minDepth": 0.276144105093466,
                "maxDepth": 0.276144105093466
              },
              {
                "type": "mousemove",
                "startTime": "2025-07-10T07:05:59.768Z",
                "endTime": "2025-07-10T07:05:59.768Z",
                "action_count": 1,
                "startPosition": {
                  "y": 212,
                  "x": 688
                },
                "endPosition": {
                  "y": 212,
                  "x": 688
                }
              },
              {
                "type": "scroll",
                "startTime": "2025-07-10T07:06:01.153Z",
                "endTime": "2025-07-10T07:06:01.153Z",
                "action_count": 1,
                "minDepth": 0.3248295968169324,
                "maxDepth": 0.3248295968169324
              },
              {
                "type": "mousemove",
                "startTime": "2025-07-10T07:06:01.218Z",
                "endTime": "2025-07-10T07:06:01.218Z",
                "action_count": 1,
                "startPosition": {
                  "y": 221,
                  "x": 686
                },
                "endPosition": {
                  "y": 221,
                  "x": 686
                }
              },
              {
                "type": "scroll",
                "startTime": "2025-07-10T07:06:04.608Z",
                "endTime": "2025-07-10T07:06:05.996Z",
                "action_count": 2,
                "minDepth": 0.42609543941191985,
                "maxDepth": 0.5033430862798198
              },
              {
                "type": "mousemove",
                "startTime": "2025-07-10T07:06:07.155Z",
                "endTime": "2025-07-10T07:06:07.655Z",
                "action_count": 2,
                "startPosition": {
                  "y": 218,
                  "x": 681
                },
                "endPosition": {
                  "y": 76,
                  "x": 633
                }
              },
              {
                "type": "scroll",
                "startTime": "2025-07-10T07:06:08.165Z",
                "endTime": "2025-07-10T07:06:08.165Z",
                "action_count": 1,
                "minDepth": 0.5677377316364411,
                "maxDepth": 0.5677377316364411
              },
              {
                "type": "mousemove",
                "startTime": "2025-07-10T07:06:08.677Z",
                "endTime": "2025-07-10T07:06:08.677Z",
                "action_count": 1,
                "startPosition": {
                  "y": 95,
                  "x": 589
                },
                "endPosition": {
                  "y": 95,
                  "x": 589
                }
              },
              {
                "type": "scroll",
                "startTime": "2025-07-10T07:06:08.787Z",
                "endTime": "2025-07-10T07:06:09.408Z",
                "action_count": 2,
                "minDepth": 0.5677377316364411,
                "maxDepth": 0.5677377316364411
              },
              {
                "type": "mousemove",
                "startTime": "2025-07-10T07:06:09.673Z",
                "endTime": "2025-07-10T07:06:16.431Z",
                "action_count": 4,
                "startPosition": {
                  "y": 250,
                  "x": 517
                },
                "endPosition": {
                  "y": 153,
                  "x": 576
                }
              }
            ]
          },
          {
            "title": "“搭子社交”：青年社交模式的新表征",
            "timestamp": "2025-07-10T07:05:52.248Z",
            "tabId": 1924860458,
            "url": "https://paper.people.com.cn/rmlt/html/2024-05/01/content_26070980.htm",
            "tabBehaviorLogs": [
              {
                "type": "mousemove",
                "startTime": "2025-07-10T07:05:42.635Z",
                "endTime": "2025-07-10T07:05:42.635Z",
                "action_count": 1,
                "startPosition": {
                  "y": 17,
                  "x": 1032
                },
                "endPosition": {
                  "y": 17,
                  "x": 1032
                }
              },
              {
                "type": "scroll",
                "startTime": "2025-07-10T07:05:43.078Z",
                "endTime": "2025-07-10T07:05:43.078Z",
                "action_count": 1,
                "minDepth": 0.23488611673975937,
                "maxDepth": 0.23488611673975937
              },
              {
                "type": "mousemove",
                "startTime": "2025-07-10T07:05:43.132Z",
                "endTime": "2025-07-10T07:05:43.132Z",
                "action_count": 1,
                "startPosition": {
                  "y": 412,
                  "x": 972
                },
                "endPosition": {
                  "y": 412,
                  "x": 972
                }
              },
              {
                "type": "scroll",
                "startTime": "2025-07-10T07:05:43.594Z",
                "endTime": "2025-07-10T07:05:43.594Z",
                "action_count": 1,
                "minDepth": 0.23488611673975937,
                "maxDepth": 0.23488611673975937
              },
              {
                "type": "mousemove",
                "startTime": "2025-07-10T07:05:43.843Z",
                "endTime": "2025-07-10T07:05:44.688Z",
                "action_count": 2,
                "startPosition": {
                  "y": 401,
                  "x": 972
                },
                "endPosition": {
                  "y": 5,
                  "x": 896
                }
              },
              {
                "type": "scroll",
                "startTime": "2025-07-10T07:05:44.956Z",
                "endTime": "2025-07-10T07:05:44.956Z",
                "action_count": 1,
                "minDepth": 0.23488611673975937,
                "maxDepth": 0.23488611673975937
              },
              {
                "type": "mousemove",
                "startTime": "2025-07-10T07:05:45.661Z",
                "endTime": "2025-07-10T07:05:45.661Z",
                "action_count": 1,
                "startPosition": {
                  "y": 246,
                  "x": 877
                },
                "endPosition": {
                  "y": 246,
                  "x": 877
                }
              },
              {
                "type": "scroll",
                "startTime": "2025-07-10T07:05:45.798Z",
                "endTime": "2025-07-10T07:05:47.025Z",
                "action_count": 2,
                "minDepth": 0.23488611673975937,
                "maxDepth": 0.23488611673975937
              },
              {
                "type": "mousemove",
                "startTime": "2025-07-10T07:05:47.074Z",
                "endTime": "2025-07-10T07:05:55.152Z",
                "action_count": 2,
                "startPosition": {
                  "y": 251,
                  "x": 882
                },
                "endPosition": {
                  "y": 167,
                  "x": 897
                }
              }
            ]
          }
        ]
      },
      "Meteora": {
        "user": {
          "session_id": "9c2f05d3-19d1-4cf6-b5a4-124ec6fba4a3",
          "user_id": "50SHBajxtge2rmatUM7OU7MPeu32",
          "group_id": "cc8f1d29-7a49-4975-95dc-7ac94aefc04b",
          "userName": "Meteora"
        },
        "windowRanges": {
          "windowStart": "2025-07-10T07:05:50.000Z",
          "windowEnd": "2025-07-10T07:08:00.000Z"
        },
        "tabHistory": [
          {
            "title": "Collaborative Platform",
            "timestamp": "2025-07-10T07:05:52.389Z",
            "tabId": 2142278855,
            "url": "https://collaborative-ai-chatbot.web.app/#/personal-dashboard/Meteora",
            "tabBehaviorLogs": [
              {
                "type": "mousemove",
                "startTime": "2025-07-10T07:05:59.328Z",
                "endTime": "2025-07-10T07:06:13.261Z",
                "action_count": 18,
                "startPosition": {
                  "y": 324,
                  "x": 632
                },
                "endPosition": {
                  "y": 170,
                  "x": 463
                }
              },
              {
                "type": "click",
                "startTime": "2025-07-10T07:06:13.723Z",
                "endTime": "2025-07-10T07:06:13.723Z",
                "action_count": 1,
                "position": {
                  "y": 172,
                  "x": 459
                }
              },
              {
                "type": "mousemove",
                "startTime": "2025-07-10T07:06:14.228Z",
                "endTime": "2025-07-10T07:06:17.477Z",
                "action_count": 6,
                "startPosition": {
                  "y": 173,
                  "x": 459
                },
                "endPosition": {
                  "y": 182,
                  "x": 436
                }
              },
              {
                "type": "click",
                "startTime": "2025-07-10T07:06:17.540Z",
                "endTime": "2025-07-10T07:06:18.356Z",
                "action_count": 2,
                "position": {
                  "y": 182,
                  "x": 435
                }
              },
              {
                "type": "mousemove",
                "startTime": "2025-07-10T07:06:18.583Z",
                "endTime": "2025-07-10T07:06:19.094Z",
                "action_count": 2,
                "startPosition": {
                  "y": 185,
                  "x": 666
                },
                "endPosition": {
                  "y": 168,
                  "x": 613
                }
              }
            ]
          }
        ]
      }
    },
    "unique_note_contents": []
  },
  "speech_counts": {
    "MehACGvYsfVaGnq5utXQupmAIji2": 5,
    "VaTnrRc18Facn5GYEcDyYNPyY7p2": 4,
    "unknown": 3,
    "50SHBajxtge2rmatUM7OU7MPeu32": 2
  },
  "speech_durations": {
    "MehACGvYsfVaGnq5utXQupmAIji2": 40.739999999999995,
    "VaTnrRc18Facn5GYEcDyYNPyY7p2": 57.620000000000005,
    "unknown": 5.66,
    "50SHBajxtge2rmatUM7OU7MPeu32": 13.94
  },
  "anomaly_history": [
    {
      "detail": {
        "evidence": "juno发言次数为0次，发言时长为0秒。\n- 浏览记录显示juno查阅了大量与'寻找“完美搭子”：轻量社交的算法匹配可能吗？'议题相关的网页，例如'搭子文化 - Google 搜索'、'搭子文化：年轻人的浅社交需求与社会变迁'、'中国年轻人以“搭子文化”应对离婚养老 | 联合早报'等。\n- 小组成员Meteora和Tark在本轮讨论中发言活跃，发言次数分别为5次和2次，发言时长分别为43.08秒和75.14秒。",
        "type": "正常参与",
        "status": "juno在本轮小组讨论中参与度极低，未进行任何发言，发言时长为0秒，远低于其他成员。但浏览记录显示其查阅了大量与'寻找“完美搭子”：轻量社交的算法匹配可能吗？'议题相关的网页，表明其在积极进行资料收集。因此，整体表现属于正常参与范围偏下。",
        "suggestion": "建议juno在接下来的讨论中积极发言，分享自己收集到的资料中的关键信息或提出问题，尝试与其他成员进行互动，例如就Meteora和Tark的资料进行讨论和比较，并尝试引导他们参与讨论。可以尝试从以下几个方面入手：1. 分享你认为最有价值的资料链接和观点；2.  针对Meteora和Tark的发言提出问题或补充观点；3.  主动总结本轮讨论的重点，并提出下一阶段的讨论方向。"
      },
      "glasses_summary": "你当前参与度低，未发言，建议积极发言，分享资料和观点。",
      "summary": "juno本轮讨论参与度低，未发言，但积极进行资料收集，整体表现属正常参与范围偏下。",
      "user_data_summary": {
        "page_view_count": 0,
        "edit_count": 0,
        "group_avg_comparison": {
          "edit_diff": 0,
          "speaking_diff": 0,
          "reply_diff": 0,
          "speaking_duration_diff": 0,
          "page_focus_diff": 0
        },
        "group_speech_distribution": {
          "other_members": {
            "50SHBajxtge2rmatUM7OU7MPeu32": {
              "duration": 43.08,
              "count": 5
            },
            "MehACGvYsfVaGnq5utXQupmAIji2": {
              "duration": 75.14,
              "count": 2
            }
          },
          "group_total_duration": 118.22,
          "current_user_speeches": 0,
          "group_total": 7,
          "current_user_duration": 0
        },
        "speaking_count": 0,
        "reply_count": 0,
        "page_switch_frequency": 0,
        "speaking_duration": 0
      },
      "start_time": "2025-07-10T07:03:35",
      "end_time": "2025-07-10T07:05:35"
    },
    {
      "detail": {
        "evidence": "在本轮2分钟的讨论中，Meteora的发言次数为5，发言时长为43.08秒。\n- Meteora积极参与了讨论，表达了自己的观点。\n-  相比前两轮零发言的记录，Meteora的参与度显著提高。\n-  相比其他成员Tark，Meteora的发言次数更多，但发言时长略短。",
        "type": "正常参与",
        "status": "Meteora在本轮讨论中表现为正常参与，发言次数和时长有所增加，积极性提升，但与小组平均水平相比仍有差距。",
        "suggestion": "继续积极参与讨论，尝试更深入地分析讨论主题，例如，结合已有的资料，提出更具体的观点或问题，并尝试与其他成员进行更深入的互动和交流。可以尝试在发言中引用具体的资料或数据来支持你的观点。"
      },
      "glasses_summary": "你当前参与度良好，建议继续积极发言，并尝试更深入地分析讨论主题。",
      "summary": "Meteora在本轮讨论中积极参与，发言次数和时长均高于前两轮，但仍有提升空间。",
      "user_data_summary": {
        "page_view_count": 4,
        "edit_count": 0,
        "group_avg_comparison": {
          "edit_diff": 0,
          "speaking_diff": 0,
          "reply_diff": 0,
          "speaking_duration_diff": 0,
          "page_focus_diff": 0
        },
        "group_speech_distribution": {
          "other_members": {
            "MehACGvYsfVaGnq5utXQupmAIji2": {
              "duration": 75.14,
              "count": 2
            },
            "VaTnrRc18Facn5GYEcDyYNPyY7p2": {
              "duration": 0,
              "count": 0
            }
          },
          "group_total_duration": 118.22,
          "current_user_speeches": 5,
          "group_total": 7,
          "current_user_duration": 43.08
        },
        "speaking_count": 5,
        "reply_count": 0,
        "page_switch_frequency": 3,
        "speaking_duration": 43.08
      },
      "start_time": "2025-07-10T07:03:35",
      "end_time": "2025-07-10T07:05:35"
    }
  ]
}